ai_subtitle_translator/__init__.py
ai_subtitle_translator/ai_translation.py
ai_subtitle_translator/app.py
ai_subtitle_translator/config.py
ai_subtitle_translator/console_utils.py
ai_subtitle_translator/main.py
ai_subtitle_translator/subtitle_handler.py
ai_subtitle_translator/translate_subtitles.py
ai_subtitle_translator/translation_validator.py
ai_subtitle_translator/utils.py
ai_subtitle_translator/validate_subtitles.py
ai_subtitle_translator-0.8.0.dist-info/METADATA
ai_subtitle_translator-0.8.0.dist-info/WHEEL
ai_subtitle_translator-0.8.0.dist-info/entry_points.txt
ai_subtitle_translator-0.8.0.dist-info/licenses/LICENSE
ai_subtitle_translator-0.8.0.dist-info/RECORD
