Metadata-Version: 2.4
Name: ai-subtitle-translator
Version: 0.8.0
Summary: Advanced subtitle translator with LLM support for converting SRT to bilingual ASS files using OpenAI, Gemini, or DeepSeek APIs
Project-URL: Homepage, https://github.com/yanp/ai-subtitle-translator
Project-URL: Repository, https://github.com/yanp/ai-subtitle-translator
Project-URL: Issues, https://github.com/yanp/ai-subtitle-translator/issues
Author-email: yanp <yanp@users.noreply.github.com>
License-File: LICENSE
Keywords: ai,ass,bazarr,deepseek,gemini,llm,openai,srt,subtitle,translation
Classifier: Development Status :: 4 - Beta
Classifier: Environment :: Console
Classifier: Environment :: Web Environment
Classifier: Intended Audience :: Developers
Classifier: License :: OSI Approved :: MIT License
Classifier: Programming Language :: Python :: 3
Classifier: Programming Language :: Python :: 3.12
Classifier: Topic :: Multimedia :: Video
Classifier: Topic :: Text Processing :: Linguistic
Requires-Python: >=3.12
Requires-Dist: fastapi[standard]>=0.116.0
Requires-Dist: google-genai>=1.25.0
Requires-Dist: json-repair>=0.49.0
Requires-Dist: openai>=1.95.0
Requires-Dist: pydantic>=2.11.0
Requires-Dist: pysubs2>=1.8.0
Requires-Dist: python-multipart>=0.0.20
Requires-Dist: rich>=14.0.0
Provides-Extra: dev
Requires-Dist: black>=25.1.0; extra == 'dev'
Requires-Dist: httpx>=0.28.0; extra == 'dev'
Requires-Dist: pytest-asyncio>=1.0.0; extra == 'dev'
Requires-Dist: pytest>=8.4.0; extra == 'dev'
Requires-Dist: ruff>=0.12.0; extra == 'dev'
